{
    "schedule": [
        {
            "cinema_id": 25,
            "sessions": [
                {
                    "kinoplan_release_id": 17790,
                    "pushkin_card": true,
                    "datetime": "2025-01-15T12:30:00Z",
                    "price": 420,
                    "format_id": 1,
                    "external_link": "https:\/\/karofilm.ru\/order\/session\/376035957"
                },
                {
                    "kinoplan_release_id": 17790,
                    "pushkin_card": true,
                    "datetime": "2025-01-15T13:40:00Z",
                    "price": 420,
                    "format_id": 1,
                    "external_link": "https:\/\/karofilm.ru\/order\/session\/376035958"
                },
                {
                    "kinoplan_release_id": 17790,
                    "pushkin_card": true,
                    "datetime": "2025-01-15T14:30:00Z",
                    "price": 420,
                    "format_id": 1,
                    "external_link": "https:\/\/karofilm.ru\/order\/session\/376035960"
                },
                {
                    "kinoplan_release_id": 17790,
                    "pushkin_card": true,
                    "datetime": "2025-01-15T15:25:00Z",
                    "price": 420,
                    "format_id": 1,
                    "external_link": "https:\/\/karofilm.ru\/order\/session\/376042325"
                },
                {
                    "kinoplan_release_id": 17790,
                    "pushkin_card": true,
                    "datetime": "2025-01-15T16:10:00Z",
                    "price": 420,
                    "format_id": 1,
                    "external_link": "https:\/\/karofilm.ru\/order\/session\/376035963"
                },
                {
                    "kinoplan_release_id": 17790,
                    "pushkin_card": true,
                    "datetime": "2025-01-15T17:00:00Z",
                    "price": 520,
                    "format_id": 1,
                    "external_link": "https:\/\/karofilm.ru\/order\/session\/376035964"
                },
                {
                    "kinoplan_release_id": 17790,
                    "pushkin_card": true,
                    "datetime": "2025-01-15T17:50:00Z",
                    "price": 520,
                    "format_id": 1,
                    "external_link": "https:\/\/karofilm.ru\/order\/session\/376032384"
                },
                {
                    "kinoplan_release_id": 17790,
                    "pushkin_card": true,
                    "datetime": "2025-01-15T18:40:00Z",
                    "price": 520,
                    "format_id": 1,
                    "external_link": "https:\/\/karofilm.ru\/order\/session\/376035967"
                },
                {
                    "kinoplan_release_id": 17790,
                    "pushkin_card": true,
                    "datetime": "2025-01-15T20:20:00Z",
                    "price": 520,
                    "format_id": 1,
                    "external_link": "https:\/\/karofilm.ru\/order\/session\/376032386"
                },
                {
                    "kinoplan_release_id": 17790,
                    "pushkin_card": true,
                    "datetime": "2025-01-16T10:25:00Z",
                    "price": 470,
                    "format_id": 1,
                    "external_link": "https:\/\/karofilm.ru\/order\/session\/376048370"
                },
                {
                    "kinoplan_release_id": 17790,
                    "pushkin_card": true,
                    "datetime": "2025-01-16T12:50:00Z",
                    "price": 470,
                    "format_id": 1,
                    "external_link": "https:\/\/karofilm.ru\/order\/session\/376048377"
                },
                {
                    "kinoplan_release_id": 17790,
                    "pushkin_card": true,
                    "datetime": "2025-01-16T14:00:00Z",
                    "price": 470,
                    "format_id": 1,
                    "external_link": "https:\/\/karofilm.ru\/order\/session\/376048380"
                },
                {
                    "kinoplan_release_id": 17790,
                    "pushkin_card": true,
                    "datetime": "2025-01-16T15:10:00Z",
                    "price": 470,
                    "format_id": 1,
                    "external_link": "https:\/\/karofilm.ru\/order\/session\/376048382"
                },
                {
                    "kinoplan_release_id": 17790,
                    "pushkin_card": true,
                    "datetime": "2025-01-16T16:25:00Z",
                    "price": 470,
                    "format_id": 1,
                    "external_link": "https:\/\/karofilm.ru\/order\/session\/376048385"
                },
                {
                    "kinoplan_release_id": 17790,
                    "pushkin_card": true,
                    "datetime": "2025-01-16T17:35:00Z",
                    "price": 570,
                    "format_id": 1,
                    "external_link": "https:\/\/karofilm.ru\/order\/session\/376048387"
                },
                {
                    "kinoplan_release_id": 17790,
                    "pushkin_card": true,
                    "datetime": "2025-01-16T18:50:00Z",
                    "price": 570,
                    "format_id": 1,
                    "external_link": "https:\/\/karofilm.ru\/order\/session\/376048390"
                },
                {
                    "kinoplan_release_id": 17790,
                    "pushkin_card": true,
                    "datetime": "2025-01-16T20:25:00Z",
                    "price": 570,
                    "format_id": 1,
                    "external_link": "https:\/\/karofilm.ru\/order\/session\/376048393"
                },
                {
                    "kinoplan_release_id": 17790,
                    "pushkin_card": true,
                    "datetime": "2025-01-17T10:25:00Z",
                    "price": 470,
                    "format_id": 1,
                    "external_link": "https:\/\/karofilm.ru\/order\/session\/376048400"
                },
                {
                    "kinoplan_release_id": 17790,
                    "pushkin_card": true,
                    "datetime": "2025-01-17T12:50:00Z",
                    "price": 470,
                    "format_id": 1,
                    "external_link": "https:\/\/karofilm.ru\/order\/session\/376048407"
                },
                {
                    "kinoplan_release_id": 17790,
                    "pushkin_card": true,
                    "datetime": "2025-01-17T14:00:00Z",
                    "price": 470,
                    "format_id": 1,
                    "external_link": "https:\/\/karofilm.ru\/order\/session\/376048410"
                },
                {
                    "kinoplan_release_id": 17790,
                    "pushkin_card": true,
                    "datetime": "2025-01-17T15:10:00Z",
                    "price": 470,
                    "format_id": 1,
                    "external_link": "https:\/\/karofilm.ru\/order\/session\/376048412"
                },
                {
                    "kinoplan_release_id": 17790,
                    "pushkin_card": true,
                    "datetime": "2025-01-17T16:25:00Z",
                    "price": 470,
                    "format_id": 1,
                    "external_link": "https:\/\/karofilm.ru\/order\/session\/376048415"
                },
                {
                    "kinoplan_release_id": 17790,
                    "pushkin_card": true,
                    "datetime": "2025-01-17T17:35:00Z",
                    "price": 570,
                    "format_id": 1,
                    "external_link": "https:\/\/karofilm.ru\/order\/session\/376048417"
                },
                {
                    "kinoplan_release_id": 17790,
                    "pushkin_card": true,
                    "datetime": "2025-01-17T18:50:00Z",
                    "price": 570,
                    "format_id": 1,
                    "external_link": "https:\/\/karofilm.ru\/order\/session\/376048420"
                },
                {
                    "kinoplan_release_id": 17790,
                    "pushkin_card": true,
                    "datetime": "2025-01-17T20:25:00Z",
                    "price": 570,
                    "format_id": 1,
                    "external_link": "https:\/\/karofilm.ru\/order\/session\/376048423"
                },
                {
                    "kinoplan_release_id": 17790,
                    "pushkin_card": true,
                    "datetime": "2025-01-18T10:25:00Z",
                    "price": 600,
                    "format_id": 1,
                    "external_link": "https:\/\/karofilm.ru\/order\/session\/376048430"
                },
                {
                    "kinoplan_release_id": 17790,
                    "pushkin_card": true,
                    "datetime": "2025-01-18T11:35:00Z",
                    "price": 600,
                    "format_id": 1,
                    "external_link": "https:\/\/karofilm.ru\/order\/session\/376048434"
                },
                {
                    "kinoplan_release_id": 17790,
                    "pushkin_card": true,
                    "datetime": "2025-01-18T12:50:00Z",
                    "price": 700,
                    "format_id": 1,
                    "external_link": "https:\/\/karofilm.ru\/order\/session\/376048437"
                },
                {
                    "kinoplan_release_id": 17790,
                    "pushkin_card": true,
                    "datetime": "2025-01-18T14:00:00Z",
                    "price": 700,
                    "format_id": 1,
                    "external_link": "https:\/\/karofilm.ru\/order\/session\/376048440"
                },
                {
                    "kinoplan_release_id": 17790,
                    "pushkin_card": true,
                    "datetime": "2025-01-18T15:10:00Z",
                    "price": 700,
                    "format_id": 1,
                    "external_link": "https:\/\/karofilm.ru\/order\/session\/376048443"
                },
                {
                    "kinoplan_release_id": 17790,
                    "pushkin_card": true,
                    "datetime": "2025-01-18T15:45:00Z",
                    "price": 700,
                    "format_id": 1,
                    "external_link": "https:\/\/karofilm.ru\/order\/session\/376048444"
                },
                {
                    "kinoplan_release_id": 17790,
                    "pushkin_card": true,
                    "datetime": "2025-01-18T16:25:00Z",
                    "price": 700,
                    "format_id": 1,
                    "external_link": "https:\/\/karofilm.ru\/order\/session\/376048446"
                },
                {
                    "kinoplan_release_id": 17790,
                    "pushkin_card": true,
                    "datetime": "2025-01-18T17:35:00Z",
                    "price": 700,
                    "format_id": 1,
                    "external_link": "https:\/\/karofilm.ru\/order\/session\/376048448"
                },
                {
                    "kinoplan_release_id": 17790,
                    "pushkin_card": true,
                    "datetime": "2025-01-18T18:50:00Z",
                    "price": 700,
                    "format_id": 1,
                    "external_link": "https:\/\/karofilm.ru\/order\/session\/376048451"
                },
                {
                    "kinoplan_release_id": 17790,
                    "pushkin_card": true,
                    "datetime": "2025-01-18T20:25:00Z",
                    "price": 700,
                    "format_id": 1,
                    "external_link": "https:\/\/karofilm.ru\/order\/session\/376048454"
                },
                {
                    "kinoplan_release_id": 17790,
                    "pushkin_card": true,
                    "datetime": "2025-01-19T10:25:00Z",
                    "price": 600,
                    "format_id": 1,
                    "external_link": "https:\/\/karofilm.ru\/order\/session\/376048461"
                },
                {
                    "kinoplan_release_id": 17790,
                    "pushkin_card": true,
                    "datetime": "2025-01-19T11:35:00Z",
                    "price": 600,
                    "format_id": 1,
                    "external_link": "https:\/\/karofilm.ru\/order\/session\/376048465"
                },
                {
                    "kinoplan_release_id": 17790,
                    "pushkin_card": true,
                    "datetime": "2025-01-19T12:50:00Z",
                    "price": 700,
                    "format_id": 1,
                    "external_link": "https:\/\/karofilm.ru\/order\/session\/376048468"
                },
                {
                    "kinoplan_release_id": 17790,
                    "pushkin_card": true,
                    "datetime": "2025-01-19T14:00:00Z",
                    "price": 700,
                    "format_id": 1,
                    "external_link": "https:\/\/karofilm.ru\/order\/session\/376048471"
                },
                {
                    "kinoplan_release_id": 17790,
                    "pushkin_card": true,
                    "datetime": "2025-01-19T15:10:00Z",
                    "price": 700,
                    "format_id": 1,
                    "external_link": "https:\/\/karofilm.ru\/order\/session\/376048474"
                },
                {
                    "kinoplan_release_id": 17790,
                    "pushkin_card": true,
                    "datetime": "2025-01-19T15:45:00Z",
                    "price": 700,
                    "format_id": 1,
                    "external_link": "https:\/\/karofilm.ru\/order\/session\/376048475"
                },
                {
                    "kinoplan_release_id": 17790,
                    "pushkin_card": true,
                    "datetime": "2025-01-19T16:25:00Z",
                    "price": 700,
                    "format_id": 1,
                    "external_link": "https:\/\/karofilm.ru\/order\/session\/376048477"
                },
                {
                    "kinoplan_release_id": 17790,
                    "pushkin_card": true,
                    "datetime": "2025-01-19T17:35:00Z",
                    "price": 700,
                    "format_id": 1,
                    "external_link": "https:\/\/karofilm.ru\/order\/session\/376048479"
                },
                {
                    "kinoplan_release_id": 17790,
                    "pushkin_card": true,
                    "datetime": "2025-01-19T18:50:00Z",
                    "price": 700,
                    "format_id": 1,
                    "external_link": "https:\/\/karofilm.ru\/order\/session\/376048482"
                },
                {
                    "kinoplan_release_id": 17790,
                    "pushkin_card": true,
                    "datetime": "2025-01-19T20:25:00Z",
                    "price": 700,
                    "format_id": 1,
                    "external_link": "https:\/\/karofilm.ru\/order\/session\/376048485"
                },
                {
                    "kinoplan_release_id": 17790,
                    "pushkin_card": true,
                    "datetime": "2025-01-20T10:25:00Z",
                    "price": 420,
                    "format_id": 1,
                    "external_link": "https:\/\/karofilm.ru\/order\/session\/376048492"
                },
                {
                    "kinoplan_release_id": 17790,
                    "pushkin_card": true,
                    "datetime": "2025-01-20T12:50:00Z",
                    "price": 420,
                    "format_id": 1,
                    "external_link": "https:\/\/karofilm.ru\/order\/session\/376048499"
                },
                {
                    "kinoplan_release_id": 17790,
                    "pushkin_card": true,
                    "datetime": "2025-01-20T14:00:00Z",
                    "price": 420,
                    "format_id": 1,
                    "external_link": "https:\/\/karofilm.ru\/order\/session\/376048502"
                },
                {
                    "kinoplan_release_id": 17790,
                    "pushkin_card": true,
                    "datetime": "2025-01-20T15:10:00Z",
                    "price": 420,
                    "format_id": 1,
                    "external_link": "https:\/\/karofilm.ru\/order\/session\/376048504"
                },
                {
                    "kinoplan_release_id": 17790,
                    "pushkin_card": true,
                    "datetime": "2025-01-20T16:25:00Z",
                    "price": 420,
                    "format_id": 1,
                    "external_link": "https:\/\/karofilm.ru\/order\/session\/376048507"
                },
                {
                    "kinoplan_release_id": 17790,
                    "pushkin_card": true,
                    "datetime": "2025-01-20T17:35:00Z",
                    "price": 520,
                    "format_id": 1,
                    "external_link": "https:\/\/karofilm.ru\/order\/session\/376048509"
                },
                {
                    "kinoplan_release_id": 17790,
                    "pushkin_card": true,
                    "datetime": "2025-01-20T18:50:00Z",
                    "price": 520,
                    "format_id": 1,
                    "external_link": "https:\/\/karofilm.ru\/order\/session\/376048512"
                },
                {
                    "kinoplan_release_id": 17790,
                    "pushkin_card": true,
                    "datetime": "2025-01-20T20:25:00Z",
                    "price": 520,
                    "format_id": 1,
                    "external_link": "https:\/\/karofilm.ru\/order\/session\/376048514"
                },
                {
                    "kinoplan_release_id": 17790,
                    "pushkin_card": true,
                    "datetime": "2025-01-21T10:25:00Z",
                    "price": 420,
                    "format_id": 1,
                    "external_link": "https:\/\/karofilm.ru\/order\/session\/376048521"
                },
                {
                    "kinoplan_release_id": 17790,
                    "pushkin_card": true,
                    "datetime": "2025-01-21T12:50:00Z",
                    "price": 420,
                    "format_id": 1,
                    "external_link": "https:\/\/karofilm.ru\/order\/session\/376048528"
                },
                {
                    "kinoplan_release_id": 17790,
                    "pushkin_card": true,
                    "datetime": "2025-01-21T14:00:00Z",
                    "price": 420,
                    "format_id": 1,
                    "external_link": "https:\/\/karofilm.ru\/order\/session\/376048531"
                },
                {
                    "kinoplan_release_id": 17790,
                    "pushkin_card": true,
                    "datetime": "2025-01-21T15:10:00Z",
                    "price": 420,
                    "format_id": 1,
                    "external_link": "https:\/\/karofilm.ru\/order\/session\/376048533"
                },
                {
                    "kinoplan_release_id": 17790,
                    "pushkin_card": true,
                    "datetime": "2025-01-21T16:25:00Z",
                    "price": 420,
                    "format_id": 1,
                    "external_link": "https:\/\/karofilm.ru\/order\/session\/376048536"
                },
                {
                    "kinoplan_release_id": 17790,
                    "pushkin_card": true,
                    "datetime": "2025-01-21T17:35:00Z",
                    "price": 520,
                    "format_id": 1,
                    "external_link": "https:\/\/karofilm.ru\/order\/session\/376048538"
                },
                {
                    "kinoplan_release_id": 17790,
                    "pushkin_card": true,
                    "datetime": "2025-01-21T18:50:00Z",
                    "price": 520,
                    "format_id": 1,
                    "external_link": "https:\/\/karofilm.ru\/order\/session\/376048541"
                },
                {
                    "kinoplan_release_id": 17790,
                    "pushkin_card": true,
                    "datetime": "2025-01-21T20:25:00Z",
                    "price": 520,
                    "format_id": 1,
                    "external_link": "https:\/\/karofilm.ru\/order\/session\/376048544"
                },
                {
                    "kinoplan_release_id": 17790,
                    "pushkin_card": true,
                    "datetime": "2025-01-22T10:25:00Z",
                    "price": 420,
                    "format_id": 1,
                    "external_link": "https:\/\/karofilm.ru\/order\/session\/376048551"
                },
                {
                    "kinoplan_release_id": 17790,
                    "pushkin_card": true,
                    "datetime": "2025-01-22T12:50:00Z",
                    "price": 420,
                    "format_id": 1,
                    "external_link": "https:\/\/karofilm.ru\/order\/session\/376048558"
                },
                {
                    "kinoplan_release_id": 17790,
                    "pushkin_card": true,
                    "datetime": "2025-01-22T14:00:00Z",
                    "price": 420,
                    "format_id": 1,
                    "external_link": "https:\/\/karofilm.ru\/order\/session\/376048561"
                },
                {
                    "kinoplan_release_id": 17790,
                    "pushkin_card": true,
                    "datetime": "2025-01-22T15:10:00Z",
                    "price": 420,
                    "format_id": 1,
                    "external_link": "https:\/\/karofilm.ru\/order\/session\/376048563"
                },
                {
                    "kinoplan_release_id": 17790,
                    "pushkin_card": true,
                    "datetime": "2025-01-22T16:25:00Z",
                    "price": 420,
                    "format_id": 1,
                    "external_link": "https:\/\/karofilm.ru\/order\/session\/376048566"
                },
                {
                    "kinoplan_release_id": 17790,
                    "pushkin_card": true,
                    "datetime": "2025-01-22T18:10:00Z",
                    "price": 520,
                    "format_id": 1,
                    "external_link": "https:\/\/karofilm.ru\/order\/session\/376050208"
                },
                {
                    "kinoplan_release_id": 17790,
                    "pushkin_card": true,
                    "datetime": "2025-01-22T20:25:00Z",
                    "price": 520,
                    "format_id": 1,
                    "external_link": "https:\/\/karofilm.ru\/order\/session\/376048574"
                },
                {
                    "kinoplan_release_id": 22253,
                    "pushkin_card": false,
                    "datetime": "2025-01-15T12:40:00Z",
                    "price": 420,
                    "format_id": 1,
                    "external_link": "https:\/\/karofilm.ru\/order\/session\/376042324"
                },
                {
                    "kinoplan_release_id": 22253,
                    "pushkin_card": false,
                    "datetime": "2025-01-15T19:30:00Z",
                    "price": 520,
                    "format_id": 1,
                    "external_link": "https:\/\/karofilm.ru\/order\/session\/376040151"
                },
                {
                    "kinoplan_release_id": 22253,
                    "pushkin_card": false,
                    "datetime": "2025-01-15T22:30:00Z",
                    "price": 520,
                    "format_id": 1,
                    "external_link": "https:\/\/karofilm.ru\/order\/session\/376040155"
                },
                {
                    "kinoplan_release_id": 22253,
                    "pushkin_card": false,
                    "datetime": "2025-01-16T19:20:00Z",
                    "price": 570,
                    "format_id": 1,
                    "external_link": "https:\/\/karofilm.ru\/order\/session\/376048392"
                },
                {
                    "kinoplan_release_id": 22253,
                    "pushkin_card": false,
                    "datetime": "2025-01-16T22:10:00Z",
                    "price": 570,
                    "format_id": 1,
                    "external_link": "https:\/\/karofilm.ru\/order\/session\/376048397"
                },
                {
                    "kinoplan_release_id": 22253,
                    "pushkin_card": false,
                    "datetime": "2025-01-17T19:20:00Z",
                    "price": 570,
                    "format_id": 1,
                    "external_link": "https:\/\/karofilm.ru\/order\/session\/376048422"
                },
                {
                    "kinoplan_release_id": 22253,
                    "pushkin_card": false,
                    "datetime": "2025-01-17T22:10:00Z",
                    "price": 570,
                    "format_id": 1,
                    "external_link": "https:\/\/karofilm.ru\/order\/session\/376048427"
                },
                {
                    "kinoplan_release_id": 22253,
                    "pushkin_card": false,
                    "datetime": "2025-01-18T19:20:00Z",
                    "price": 700,
                    "format_id": 1,
                    "external_link": "https:\/\/karofilm.ru\/order\/session\/376048453"
                },
                {
                    "kinoplan_release_id": 22253,
                    "pushkin_card": false,
                    "datetime": "2025-01-18T22:10:00Z",
                    "price": 700,
                    "format_id": 1,
                    "external_link": "https:\/\/karofilm.ru\/order\/session\/376048458"
                },
                {
                    "kinoplan_release_id": 22253,
                    "pushkin_card": false,
                    "datetime": "2025-01-19T19:20:00Z",
                    "price": 700,
                    "format_id": 1,
                    "external_link": "https:\/\/karofilm.ru\/order\/session\/376048484"
                },
                {
                    "kinoplan_release_id": 22253,
                    "pushkin_card": false,
                    "datetime": "2025-01-19T22:10:00Z",
                    "price": 700,
                    "format_id": 1,
                    "external_link": "https:\/\/karofilm.ru\/order\/session\/376048489"
                },
                {
                    "kinoplan_release_id": 22253,
                    "pushkin_card": false,
                    "datetime": "2025-01-20T16:15:00Z",
                    "price": 420,
                    "format_id": 1,
                    "external_link": "https:\/\/karofilm.ru\/order\/session\/376048506"
                },
                {
                    "kinoplan_release_id": 22253,
                    "pushkin_card": false,
                    "datetime": "2025-01-20T20:50:00Z",
                    "price": 520,
                    "format_id": 1,
                    "external_link": "https:\/\/karofilm.ru\/order\/session\/376048516"
                },
                {
                    "kinoplan_release_id": 22253,
                    "pushkin_card": false,
                    "datetime": "2025-01-21T19:20:00Z",
                    "price": 520,
                    "format_id": 1,
                    "external_link": "https:\/\/karofilm.ru\/order\/session\/376048543"
                },
                {
                    "kinoplan_release_id": 22253,
                    "pushkin_card": false,
                    "datetime": "2025-01-21T22:10:00Z",
                    "price": 520,
                    "format_id": 1,
                    "external_link": "https:\/\/karofilm.ru\/order\/session\/376048548"
                },
                {
                    "kinoplan_release_id": 22253,
                    "pushkin_card": false,
                    "datetime": "2025-01-22T19:20:00Z",
                    "price": 520,
                    "format_id": 1,
                    "external_link": "https:\/\/karofilm.ru\/order\/session\/376048573"
                },
                {
                    "kinoplan_release_id": 22253,
                    "pushkin_card": false,
                    "datetime": "2025-01-22T22:10:00Z",
                    "price": 520,
                    "format_id": 1,
                    "external_link": "https:\/\/karofilm.ru\/order\/session\/376048578"
                },
                {
                    "kinoplan_release_id": 20984,
                    "pushkin_card": true,
                    "datetime": "2025-01-15T13:25:00Z",
                    "price": 420,
                    "format_id": 1,
                    "external_link": "https:\/\/karofilm.ru\/order\/session\/376032381"
                },
                {
                    "kinoplan_release_id": 20984,
                    "pushkin_card": true,
                    "datetime": "2025-01-15T14:50:00Z",
                    "price": 420,
                    "format_id": 1,
                    "external_link": "https:\/\/karofilm.ru\/order\/session\/376035961"
                },
                {
                    "kinoplan_release_id": 20984,
                    "pushkin_card": true,
                    "datetime": "2025-01-15T16:20:00Z",
                    "price": 420,
                    "format_id": 1,
                    "external_link": "https:\/\/karofilm.ru\/order\/session\/376032383"
                },
                {
                    "kinoplan_release_id": 20984,
                    "pushkin_card": true,
                    "datetime": "2025-01-15T17:40:00Z",
                    "price": 520,
                    "format_id": 1,
                    "external_link": "https:\/\/karofilm.ru\/order\/session\/376035965"
                },
                {
                    "kinoplan_release_id": 20984,
                    "pushkin_card": true,
                    "datetime": "2025-01-15T19:15:00Z",
                    "price": 520,
                    "format_id": 1,
                    "external_link": "https:\/\/karofilm.ru\/order\/session\/376032385"
                },
                {
                    "kinoplan_release_id": 20984,
                    "pushkin_card": true,
                    "datetime": "2025-01-15T20:40:00Z",
                    "price": 520,
                    "format_id": 1,
                    "external_link": "https:\/\/karofilm.ru\/order\/session\/376035968"
                },
                {
                    "kinoplan_release_id": 20984,
                    "pushkin_card": true,
                    "datetime": "2025-01-16T11:10:00Z",
                    "price": 470,
                    "format_id": 1,
                    "external_link": "https:\/\/karofilm.ru\/order\/session\/376048373"
                },
                {
                    "kinoplan_release_id": 20984,
                    "pushkin_card": true,
                    "datetime": "2025-01-16T13:25:00Z",
                    "price": 470,
                    "format_id": 1,
                    "external_link": "https:\/\/karofilm.ru\/order\/session\/376048379"
                },
                {
                    "kinoplan_release_id": 20984,
                    "pushkin_card": true,
                    "datetime": "2025-01-16T14:50:00Z",
                    "price": 470,
                    "format_id": 1,
                    "external_link": "https:\/\/karofilm.ru\/order\/session\/376048381"
                },
                {
                    "kinoplan_release_id": 20984,
                    "pushkin_card": true,
                    "datetime": "2025-01-16T16:15:00Z",
                    "price": 470,
                    "format_id": 1,
                    "external_link": "https:\/\/karofilm.ru\/order\/session\/376048384"
                },
                {
                    "kinoplan_release_id": 20984,
                    "pushkin_card": true,
                    "datetime": "2025-01-16T17:40:00Z",
                    "price": 570,
                    "format_id": 1,
                    "external_link": "https:\/\/karofilm.ru\/order\/session\/376048388"
                },
                {
                    "kinoplan_release_id": 20984,
                    "pushkin_card": true,
                    "datetime": "2025-01-16T19:05:00Z",
                    "price": 570,
                    "format_id": 1,
                    "external_link": "https:\/\/karofilm.ru\/order\/session\/376048391"
                },
                {
                    "kinoplan_release_id": 20984,
                    "pushkin_card": true,
                    "datetime": "2025-01-16T20:45:00Z",
                    "price": 570,
                    "format_id": 1,
                    "external_link": "https:\/\/karofilm.ru\/order\/session\/376048394"
                },
                {
                    "kinoplan_release_id": 20984,
                    "pushkin_card": true,
                    "datetime": "2025-01-17T11:10:00Z",
                    "price": 470,
                    "format_id": 1,
                    "external_link": "https:\/\/karofilm.ru\/order\/session\/376048403"
                },
                {
                    "kinoplan_release_id": 20984,
                    "pushkin_card": true,
                    "datetime": "2025-01-17T13:25:00Z",
                    "price": 470,
                    "format_id": 1,
                    "external_link": "https:\/\/karofilm.ru\/order\/session\/376048409"
                },
                {
                    "kinoplan_release_id": 20984,
                    "pushkin_card": true,
                    "datetime": "2025-01-17T14:50:00Z",
                    "price": 470,
                    "format_id": 1,
                    "external_link": "https:\/\/karofilm.ru\/order\/session\/376048411"
                },
                {
                    "kinoplan_release_id": 20984,
                    "pushkin_card": true,
                    "datetime": "2025-01-17T16:15:00Z",
                    "price": 470,
                    "format_id": 1,
                    "external_link": "https:\/\/karofilm.ru\/order\/session\/376048414"
                },
                {
                    "kinoplan_release_id": 20984,
                    "pushkin_card": true,
                    "datetime": "2025-01-17T17:40:00Z",
                    "price": 570,
                    "format_id": 1,
                    "external_link": "https:\/\/karofilm.ru\/order\/session\/376048418"
                },
                {
                    "kinoplan_release_id": 20984,
                    "pushkin_card": true,
                    "datetime": "2025-01-17T19:05:00Z",
                    "price": 570,
                    "format_id": 1,
                    "external_link": "https:\/\/karofilm.ru\/order\/session\/376048421"
                },
                {
                    "kinoplan_release_id": 20984,
                    "pushkin_card": true,
                    "datetime": "2025-01-17T20:45:00Z",
                    "price": 570,
                    "format_id": 1,
                    "external_link": "https:\/\/karofilm.ru\/order\/session\/376048424"
                },
                {
                    "kinoplan_release_id": 20984,
                    "pushkin_card": true,
                    "datetime": "2025-01-18T10:50:00Z",
                    "price": 600,
                    "format_id": 1,
                    "external_link": "https:\/\/karofilm.ru\/order\/session\/376048431"
                },
                {
                    "kinoplan_release_id": 20984,
                    "pushkin_card": true,
                    "datetime": "2025-01-18T13:25:00Z",
                    "price": 700,
                    "format_id": 1,
                    "external_link": "https:\/\/karofilm.ru\/order\/session\/376048438"
                },
                {
                    "kinoplan_release_id": 20984,
                    "pushkin_card": true,
                    "datetime": "2025-01-18T14:50:00Z",
                    "price": 700,
                    "format_id": 1,
                    "external_link": "https:\/\/karofilm.ru\/order\/session\/376048442"
                },
                {
                    "kinoplan_release_id": 20984,
                    "pushkin_card": true,
                    "datetime": "2025-01-18T16:15:00Z",
                    "price": 700,
                    "format_id": 1,
                    "external_link": "https:\/\/karofilm.ru\/order\/session\/376048445"
                },
                {
                    "kinoplan_release_id": 20984,
                    "pushkin_card": true,
                    "datetime": "2025-01-18T17:40:00Z",
                    "price": 700,
                    "format_id": 1,
                    "external_link": "https:\/\/karofilm.ru\/order\/session\/376048449"
                },
                {
                    "kinoplan_release_id": 20984,
                    "pushkin_card": true,
                    "datetime": "2025-01-18T19:05:00Z",
                    "price": 700,
                    "format_id": 1,
                    "external_link": "https:\/\/karofilm.ru\/order\/session\/376048452"
                },
                {
                    "kinoplan_release_id": 20984,
                    "pushkin_card": true,
                    "datetime": "2025-01-18T20:45:00Z",
                    "price": 700,
                    "format_id": 1,
                    "external_link": "https:\/\/karofilm.ru\/order\/session\/376048455"
                },
                {
                    "kinoplan_release_id": 20984,
                    "pushkin_card": true,
                    "datetime": "2025-01-19T10:50:00Z",
                    "price": 600,
                    "format_id": 1,
                    "external_link": "https:\/\/karofilm.ru\/order\/session\/376048462"
                },
                {
                    "kinoplan_release_id": 20984,
                    "pushkin_card": true,
                    "datetime": "2025-01-19T13:25:00Z",
                    "price": 700,
                    "format_id": 1,
                    "external_link": "https:\/\/karofilm.ru\/order\/session\/376048469"
                },
                {
                    "kinoplan_release_id": 20984,
                    "pushkin_card": true,
                    "datetime": "2025-01-19T14:50:00Z",
                    "price": 700,
                    "format_id": 1,
                    "external_link": "https:\/\/karofilm.ru\/order\/session\/376048473"
                },
                {
                    "kinoplan_release_id": 20984,
                    "pushkin_card": true,
                    "datetime": "2025-01-19T16:15:00Z",
                    "price": 700,
                    "format_id": 1,
                    "external_link": "https:\/\/karofilm.ru\/order\/session\/376048476"
                },
                {
                    "kinoplan_release_id": 20984,
                    "pushkin_card": true,
                    "datetime": "2025-01-19T17:40:00Z",
                    "price": 700,
                    "format_id": 1,
                    "external_link": "https:\/\/karofilm.ru\/order\/session\/376048480"
                },
                {
                    "kinoplan_release_id": 20984,
                    "pushkin_card": true,
                    "datetime": "2025-01-19T19:05:00Z",
                    "price": 700,
                    "format_id": 1,
                    "external_link": "https:\/\/karofilm.ru\/order\/session\/376048483"
                },
                {
                    "kinoplan_release_id": 20984,
                    "pushkin_card": true,
                    "datetime": "2025-01-19T20:45:00Z",
                    "price": 700,
                    "format_id": 1,
                    "external_link": "https:\/\/karofilm.ru\/order\/session\/376048486"
                },
                {
                    "kinoplan_release_id": 20984,
                    "pushkin_card": true,
                    "datetime": "2025-01-20T11:10:00Z",
                    "price": 420,
                    "format_id": 1,
                    "external_link": "https:\/\/karofilm.ru\/order\/session\/376048495"
                },
                {
                    "kinoplan_release_id": 20984,
                    "pushkin_card": true,
                    "datetime": "2025-01-20T13:25:00Z",
                    "price": 420,
                    "format_id": 1,
                    "external_link": "https:\/\/karofilm.ru\/order\/session\/376048501"
                },
                {
                    "kinoplan_release_id": 20984,
                    "pushkin_card": true,
                    "datetime": "2025-01-20T14:50:00Z",
                    "price": 420,
                    "format_id": 1,
                    "external_link": "https:\/\/karofilm.ru\/order\/session\/376048503"
                },
                {
                    "kinoplan_release_id": 20984,
                    "pushkin_card": true,
                    "datetime": "2025-01-20T17:40:00Z",
                    "price": 520,
                    "format_id": 1,
                    "external_link": "https:\/\/karofilm.ru\/order\/session\/376048510"
                },
                {
                    "kinoplan_release_id": 20984,
                    "pushkin_card": true,
                    "datetime": "2025-01-20T19:05:00Z",
                    "price": 520,
                    "format_id": 1,
                    "external_link": "https:\/\/karofilm.ru\/order\/session\/376048513"
                },
                {
                    "kinoplan_release_id": 20984,
                    "pushkin_card": true,
                    "datetime": "2025-01-20T20:45:00Z",
                    "price": 520,
                    "format_id": 1,
                    "external_link": "https:\/\/karofilm.ru\/order\/session\/376048515"
                },
                {
                    "kinoplan_release_id": 20984,
                    "pushkin_card": true,
                    "datetime": "2025-01-21T11:10:00Z",
                    "price": 420,
                    "format_id": 1,
                    "external_link": "https:\/\/karofilm.ru\/order\/session\/376048524"
                },
                {
                    "kinoplan_release_id": 20984,
                    "pushkin_card": true,
                    "datetime": "2025-01-21T13:25:00Z",
                    "price": 420,
                    "format_id": 1,
                    "external_link": "https:\/\/karofilm.ru\/order\/session\/376048530"
                },
                {
                    "kinoplan_release_id": 20984,
                    "pushkin_card": true,
                    "datetime": "2025-01-21T14:50:00Z",
                    "price": 420,
                    "format_id": 1,
                    "external_link": "https:\/\/karofilm.ru\/order\/session\/376048532"
                },
                {
                    "kinoplan_release_id": 20984,
                    "pushkin_card": true,
                    "datetime": "2025-01-21T16:15:00Z",
                    "price": 420,
                    "format_id": 1,
                    "external_link": "https:\/\/karofilm.ru\/order\/session\/376048535"
                },
                {
                    "kinoplan_release_id": 20984,
                    "pushkin_card": true,
                    "datetime": "2025-01-21T17:40:00Z",
                    "price": 520,
                    "format_id": 1,
                    "external_link": "https:\/\/karofilm.ru\/order\/session\/376048539"
                },
                {
                    "kinoplan_release_id": 20984,
                    "pushkin_card": true,
                    "datetime": "2025-01-21T19:05:00Z",
                    "price": 520,
                    "format_id": 1,
                    "external_link": "https:\/\/karofilm.ru\/order\/session\/376048542"
                },
                {
                    "kinoplan_release_id": 20984,
                    "pushkin_card": true,
                    "datetime": "2025-01-21T20:45:00Z",
                    "price": 520,
                    "format_id": 1,
                    "external_link": "https:\/\/karofilm.ru\/order\/session\/376048545"
                },
                {
                    "kinoplan_release_id": 20984,
                    "pushkin_card": true,
                    "datetime": "2025-01-22T11:10:00Z",
                    "price": 420,
                    "format_id": 1,
                    "external_link": "https:\/\/karofilm.ru\/order\/session\/376048554"
                },
                {
                    "kinoplan_release_id": 20984,
                    "pushkin_card": true,
                    "datetime": "2025-01-22T13:25:00Z",
                    "price": 420,
                    "format_id": 1,
                    "external_link": "https:\/\/karofilm.ru\/order\/session\/376048560"
                },
                {
                    "kinoplan_release_id": 20984,
                    "pushkin_card": true,
                    "datetime": "2025-01-22T14:50:00Z",
                    "price": 420,
                    "format_id": 1,
                    "external_link": "https:\/\/karofilm.ru\/order\/session\/376048562"
                },
                {
                    "kinoplan_release_id": 20984,
                    "pushkin_card": true,
                    "datetime": "2025-01-22T16:15:00Z",
                    "price": 420,
                    "format_id": 1,
                    "external_link": "https:\/\/karofilm.ru\/order\/session\/376048565"
                },
                {
                    "kinoplan_release_id": 20984,
                    "pushkin_card": true,
                    "datetime": "2025-01-22T17:40:00Z",
                    "price": 520,
                    "format_id": 1,
                    "external_link": "https:\/\/karofilm.ru\/order\/session\/376048569"
                },
                {
                    "kinoplan_release_id": 20984,
                    "pushkin_card": true,
                    "datetime": "2025-01-22T19:05:00Z",
                    "price": 520,
                    "format_id": 1,
                    "external_link": "https:\/\/karofilm.ru\/order\/session\/376048572"
                },
                {
                    "kinoplan_release_id": 20984,
                    "pushkin_card": true,
                    "datetime": "2025-01-22T20:45:00Z",
                    "price": 520,
                    "format_id": 1,
                    "external_link": "https:\/\/karofilm.ru\/order\/session\/376048575"
                },
                {
                    "kinoplan_release_id": 21419,
                    "pushkin_card": true,
                    "datetime": "2025-01-15T13:50:00Z",
                    "price": 420,
                    "format_id": 1,
                    "external_link": "https:\/\/karofilm.ru\/order\/session\/376035959"
                },
                {
                    "kinoplan_release_id": 20442,
                    "pushkin_card": true,
                    "datetime": "2025-01-15T15:50:00Z",
                    "price": 420,
                    "format_id": 1,
                    "external_link": "https:\/\/karofilm.ru\/order\/session\/376035962"
                },
                {
                    "kinoplan_release_id": 20442,
                    "pushkin_card": true,
                    "datetime": "2025-01-16T12:15:00Z",
                    "price": 470,
                    "format_id": 1,
                    "external_link": "https:\/\/karofilm.ru\/order\/session\/376048375"
                },
                {
                    "kinoplan_release_id": 20442,
                    "pushkin_card": true,
                    "datetime": "2025-01-17T12:15:00Z",
                    "price": 470,
                    "format_id": 1,
                    "external_link": "https:\/\/karofilm.ru\/order\/session\/376048405"
                },
                {
                    "kinoplan_release_id": 20442,
                    "pushkin_card": true,
                    "datetime": "2025-01-18T12:15:00Z",
                    "price": 700,
                    "format_id": 1,
                    "external_link": "https:\/\/karofilm.ru\/order\/session\/376048435"
                },
                {
                    "kinoplan_release_id": 20442,
                    "pushkin_card": true,
                    "datetime": "2025-01-19T12:15:00Z",
                    "price": 700,
                    "format_id": 1,
                    "external_link": "https:\/\/karofilm.ru\/order\/session\/376048466"
                },
                {
                    "kinoplan_release_id": 20442,
                    "pushkin_card": true,
                    "datetime": "2025-01-21T12:15:00Z",
                    "price": 420,
                    "format_id": 1,
                    "external_link": "https:\/\/karofilm.ru\/order\/session\/376048526"
                },
                {
                    "kinoplan_release_id": 20442,
                    "pushkin_card": true,
                    "datetime": "2025-01-22T12:15:00Z",
                    "price": 420,
                    "format_id": 1,
                    "external_link": "https:\/\/karofilm.ru\/order\/session\/376048556"
                },
                {
                    "kinoplan_release_id": 21759,
                    "pushkin_card": true,
                    "datetime": "2025-01-15T18:00:00Z",
                    "price": 520,
                    "format_id": 1,
                    "external_link": "https:\/\/karofilm.ru\/order\/session\/376035966"
                },
                {
                    "kinoplan_release_id": 21759,
                    "pushkin_card": true,
                    "datetime": "2025-01-15T22:20:00Z",
                    "price": 520,
                    "format_id": 1,
                    "external_link": "https:\/\/karofilm.ru\/order\/session\/376035969"
                },
                {
                    "kinoplan_release_id": 21759,
                    "pushkin_card": true,
                    "datetime": "2025-01-16T12:30:00Z",
                    "price": 470,
                    "format_id": 1,
                    "external_link": "https:\/\/karofilm.ru\/order\/session\/376048376"
                },
                {
                    "kinoplan_release_id": 21759,
                    "pushkin_card": true,
                    "datetime": "2025-01-16T21:15:00Z",
                    "price": 570,
                    "format_id": 1,
                    "external_link": "https:\/\/karofilm.ru\/order\/session\/376048395"
                },
                {
                    "kinoplan_release_id": 21759,
                    "pushkin_card": true,
                    "datetime": "2025-01-17T12:30:00Z",
                    "price": 470,
                    "format_id": 1,
                    "external_link": "https:\/\/karofilm.ru\/order\/session\/376048406"
                },
                {
                    "kinoplan_release_id": 21759,
                    "pushkin_card": true,
                    "datetime": "2025-01-17T21:15:00Z",
                    "price": 570,
                    "format_id": 1,
                    "external_link": "https:\/\/karofilm.ru\/order\/session\/376048425"
                },
                {
                    "kinoplan_release_id": 21759,
                    "pushkin_card": true,
                    "datetime": "2025-01-18T12:30:00Z",
                    "price": 700,
                    "format_id": 1,
                    "external_link": "https:\/\/karofilm.ru\/order\/session\/376048436"
                },
                {
                    "kinoplan_release_id": 21759,
                    "pushkin_card": true,
                    "datetime": "2025-01-18T21:15:00Z",
                    "price": 700,
                    "format_id": 1,
                    "external_link": "https:\/\/karofilm.ru\/order\/session\/376048456"
                },
                {
                    "kinoplan_release_id": 21759,
                    "pushkin_card": true,
                    "datetime": "2025-01-19T21:15:00Z",
                    "price": 700,
                    "format_id": 1,
                    "external_link": "https:\/\/karofilm.ru\/order\/session\/376048487"
                },
                {
                    "kinoplan_release_id": 21759,
                    "pushkin_card": true,
                    "datetime": "2025-01-20T12:30:00Z",
                    "price": 420,
                    "format_id": 1,
                    "external_link": "https:\/\/karofilm.ru\/order\/session\/376048498"
                },
                {
                    "kinoplan_release_id": 21759,
                    "pushkin_card": true,
                    "datetime": "2025-01-20T21:15:00Z",
                    "price": 520,
                    "format_id": 1,
                    "external_link": "https:\/\/karofilm.ru\/order\/session\/376048517"
                },
                {
                    "kinoplan_release_id": 21759,
                    "pushkin_card": true,
                    "datetime": "2025-01-21T12:30:00Z",
                    "price": 420,
                    "format_id": 1,
                    "external_link": "https:\/\/karofilm.ru\/order\/session\/376048527"
                },
                {
                    "kinoplan_release_id": 21759,
                    "pushkin_card": true,
                    "datetime": "2025-01-21T21:15:00Z",
                    "price": 520,
                    "format_id": 1,
                    "external_link": "https:\/\/karofilm.ru\/order\/session\/376048546"
                },
                {
                    "kinoplan_release_id": 21759,
                    "pushkin_card": true,
                    "datetime": "2025-01-22T12:30:00Z",
                    "price": 420,
                    "format_id": 1,
                    "external_link": "https:\/\/karofilm.ru\/order\/session\/376048557"
                },
                {
                    "kinoplan_release_id": 21759,
                    "pushkin_card": true,
                    "datetime": "2025-01-22T21:20:00Z",
                    "price": 520,
                    "format_id": 1,
                    "external_link": "https:\/\/karofilm.ru\/order\/session\/376050209"
                },
                {
                    "kinoplan_release_id": 22022,
                    "pushkin_card": false,
                    "datetime": "2025-01-15T20:10:00Z",
                    "price": 520,
                    "format_id": 1,
                    "external_link": "https:\/\/karofilm.ru\/order\/session\/376040152"
                },
                {
                    "kinoplan_release_id": 22022,
                    "pushkin_card": false,
                    "datetime": "2025-01-15T22:50:00Z",
                    "price": 520,
                    "format_id": 1,
                    "external_link": "https:\/\/karofilm.ru\/order\/session\/376040156"
                },
                {
                    "kinoplan_release_id": 22022,
                    "pushkin_card": false,
                    "datetime": "2025-01-16T22:50:00Z",
                    "price": 570,
                    "format_id": 1,
                    "external_link": "https:\/\/karofilm.ru\/order\/session\/376048398"
                },
                {
                    "kinoplan_release_id": 22022,
                    "pushkin_card": false,
                    "datetime": "2025-01-17T22:50:00Z",
                    "price": 570,
                    "format_id": 1,
                    "external_link": "https:\/\/karofilm.ru\/order\/session\/376048428"
                },
                {
                    "kinoplan_release_id": 22022,
                    "pushkin_card": false,
                    "datetime": "2025-01-18T22:50:00Z",
                    "price": 700,
                    "format_id": 1,
                    "external_link": "https:\/\/karofilm.ru\/order\/session\/376048459"
                },
                {
                    "kinoplan_release_id": 22022,
                    "pushkin_card": false,
                    "datetime": "2025-01-19T22:50:00Z",
                    "price": 700,
                    "format_id": 1,
                    "external_link": "https:\/\/karofilm.ru\/order\/session\/376048490"
                },
                {
                    "kinoplan_release_id": 22022,
                    "pushkin_card": false,
                    "datetime": "2025-01-20T22:50:00Z",
                    "price": 520,
                    "format_id": 1,
                    "external_link": "https:\/\/karofilm.ru\/order\/session\/376048519"
                },
                {
                    "kinoplan_release_id": 22022,
                    "pushkin_card": false,
                    "datetime": "2025-01-21T22:50:00Z",
                    "price": 520,
                    "format_id": 1,
                    "external_link": "https:\/\/karofilm.ru\/order\/session\/376048549"
                },
                {
                    "kinoplan_release_id": 22022,
                    "pushkin_card": false,
                    "datetime": "2025-01-22T22:50:00Z",
                    "price": 520,
                    "format_id": 1,
                    "external_link": "https:\/\/karofilm.ru\/order\/session\/376048579"
                },
                {
                    "kinoplan_release_id": 20959,
                    "pushkin_card": false,
                    "datetime": "2025-01-15T21:10:00Z",
                    "price": 520,
                    "format_id": 1,
                    "external_link": "https:\/\/karofilm.ru\/order\/session\/376040153"
                },
                {
                    "kinoplan_release_id": 20959,
                    "pushkin_card": false,
                    "datetime": "2025-01-16T21:50:00Z",
                    "price": 570,
                    "format_id": 1,
                    "external_link": "https:\/\/karofilm.ru\/order\/session\/376048396"
                },
                {
                    "kinoplan_release_id": 20959,
                    "pushkin_card": false,
                    "datetime": "2025-01-17T21:50:00Z",
                    "price": 570,
                    "format_id": 1,
                    "external_link": "https:\/\/karofilm.ru\/order\/session\/376048426"
                },
                {
                    "kinoplan_release_id": 20959,
                    "pushkin_card": false,
                    "datetime": "2025-01-18T21:50:00Z",
                    "price": 700,
                    "format_id": 1,
                    "external_link": "https:\/\/karofilm.ru\/order\/session\/376048457"
                },
                {
                    "kinoplan_release_id": 20959,
                    "pushkin_card": false,
                    "datetime": "2025-01-19T21:50:00Z",
                    "price": 700,
                    "format_id": 1,
                    "external_link": "https:\/\/karofilm.ru\/order\/session\/376048488"
                },
                {
                    "kinoplan_release_id": 20959,
                    "pushkin_card": false,
                    "datetime": "2025-01-20T21:50:00Z",
                    "price": 520,
                    "format_id": 1,
                    "external_link": "https:\/\/karofilm.ru\/order\/session\/376048518"
                },
                {
                    "kinoplan_release_id": 20959,
                    "pushkin_card": false,
                    "datetime": "2025-01-21T21:50:00Z",
                    "price": 520,
                    "format_id": 1,
                    "external_link": "https:\/\/karofilm.ru\/order\/session\/376048547"
                },
                {
                    "kinoplan_release_id": 20959,
                    "pushkin_card": false,
                    "datetime": "2025-01-22T21:50:00Z",
                    "price": 520,
                    "format_id": 1,
                    "external_link": "https:\/\/karofilm.ru\/order\/session\/376048577"
                },
                {
                    "kinoplan_release_id": 22298,
                    "pushkin_card": false,
                    "datetime": "2025-01-15T22:00:00Z",
                    "price": 520,
                    "format_id": 1,
                    "external_link": "https:\/\/karofilm.ru\/order\/session\/376040154"
                },
                {
                    "kinoplan_release_id": 22624,
                    "pushkin_card": false,
                    "datetime": "2025-01-16T10:10:00Z",
                    "price": 470,
                    "format_id": 1,
                    "external_link": "https:\/\/karofilm.ru\/order\/session\/376048369"
                },
                {
                    "kinoplan_release_id": 22624,
                    "pushkin_card": false,
                    "datetime": "2025-01-16T16:00:00Z",
                    "price": 470,
                    "format_id": 1,
                    "external_link": "https:\/\/karofilm.ru\/order\/session\/376048383"
                },
                {
                    "kinoplan_release_id": 22624,
                    "pushkin_card": false,
                    "datetime": "2025-01-17T10:10:00Z",
                    "price": 470,
                    "format_id": 1,
                    "external_link": "https:\/\/karofilm.ru\/order\/session\/376048399"
                },
                {
                    "kinoplan_release_id": 22624,
                    "pushkin_card": false,
                    "datetime": "2025-01-17T16:00:00Z",
                    "price": 470,
                    "format_id": 1,
                    "external_link": "https:\/\/karofilm.ru\/order\/session\/376048413"
                },
                {
                    "kinoplan_release_id": 22624,
                    "pushkin_card": false,
                    "datetime": "2025-01-18T10:10:00Z",
                    "price": 600,
                    "format_id": 1,
                    "external_link": "https:\/\/karofilm.ru\/order\/session\/376048429"
                },
                {
                    "kinoplan_release_id": 22624,
                    "pushkin_card": false,
                    "datetime": "2025-01-18T13:40:00Z",
                    "price": 700,
                    "format_id": 1,
                    "external_link": "https:\/\/karofilm.ru\/order\/session\/376048439"
                },
                {
                    "kinoplan_release_id": 22624,
                    "pushkin_card": false,
                    "datetime": "2025-01-19T10:10:00Z",
                    "price": 600,
                    "format_id": 1,
                    "external_link": "https:\/\/karofilm.ru\/order\/session\/376048460"
                },
                {
                    "kinoplan_release_id": 22624,
                    "pushkin_card": false,
                    "datetime": "2025-01-19T13:40:00Z",
                    "price": 700,
                    "format_id": 1,
                    "external_link": "https:\/\/karofilm.ru\/order\/session\/376048470"
                },
                {
                    "kinoplan_release_id": 22624,
                    "pushkin_card": false,
                    "datetime": "2025-01-20T10:10:00Z",
                    "price": 420,
                    "format_id": 1,
                    "external_link": "https:\/\/karofilm.ru\/order\/session\/376048491"
                },
                {
                    "kinoplan_release_id": 22624,
                    "pushkin_card": false,
                    "datetime": "2025-01-20T16:00:00Z",
                    "price": 420,
                    "format_id": 1,
                    "external_link": "https:\/\/karofilm.ru\/order\/session\/376048505"
                },
                {
                    "kinoplan_release_id": 22624,
                    "pushkin_card": false,
                    "datetime": "2025-01-21T10:10:00Z",
                    "price": 420,
                    "format_id": 1,
                    "external_link": "https:\/\/karofilm.ru\/order\/session\/376048520"
                },
                {
                    "kinoplan_release_id": 22624,
                    "pushkin_card": false,
                    "datetime": "2025-01-21T16:00:00Z",
                    "price": 420,
                    "format_id": 1,
                    "external_link": "https:\/\/karofilm.ru\/order\/session\/376048534"
                },
                {
                    "kinoplan_release_id": 22624,
                    "pushkin_card": false,
                    "datetime": "2025-01-22T10:10:00Z",
                    "price": 420,
                    "format_id": 1,
                    "external_link": "https:\/\/karofilm.ru\/order\/session\/376048550"
                },
                {
                    "kinoplan_release_id": 22624,
                    "pushkin_card": false,
                    "datetime": "2025-01-22T16:00:00Z",
                    "price": 420,
                    "format_id": 1,
                    "external_link": "https:\/\/karofilm.ru\/order\/session\/376048564"
                },
                {
                    "kinoplan_release_id": 22371,
                    "pushkin_card": false,
                    "datetime": "2025-01-16T10:40:00Z",
                    "price": 470,
                    "format_id": 1,
                    "external_link": "https:\/\/karofilm.ru\/order\/session\/376048371"
                },
                {
                    "kinoplan_release_id": 22371,
                    "pushkin_card": false,
                    "datetime": "2025-01-16T18:10:00Z",
                    "price": 570,
                    "format_id": 1,
                    "external_link": "https:\/\/karofilm.ru\/order\/session\/376048389"
                },
                {
                    "kinoplan_release_id": 22371,
                    "pushkin_card": false,
                    "datetime": "2025-01-17T10:40:00Z",
                    "price": 470,
                    "format_id": 1,
                    "external_link": "https:\/\/karofilm.ru\/order\/session\/376048401"
                },
                {
                    "kinoplan_release_id": 22371,
                    "pushkin_card": false,
                    "datetime": "2025-01-17T18:10:00Z",
                    "price": 570,
                    "format_id": 1,
                    "external_link": "https:\/\/karofilm.ru\/order\/session\/376048419"
                },
                {
                    "kinoplan_release_id": 22371,
                    "pushkin_card": false,
                    "datetime": "2025-01-18T18:10:00Z",
                    "price": 700,
                    "format_id": 1,
                    "external_link": "https:\/\/karofilm.ru\/order\/session\/376048450"
                },
                {
                    "kinoplan_release_id": 22371,
                    "pushkin_card": false,
                    "datetime": "2025-01-19T18:10:00Z",
                    "price": 700,
                    "format_id": 1,
                    "external_link": "https:\/\/karofilm.ru\/order\/session\/376048481"
                },
                {
                    "kinoplan_release_id": 22371,
                    "pushkin_card": false,
                    "datetime": "2025-01-20T10:40:00Z",
                    "price": 420,
                    "format_id": 1,
                    "external_link": "https:\/\/karofilm.ru\/order\/session\/376048493"
                },
                {
                    "kinoplan_release_id": 22371,
                    "pushkin_card": false,
                    "datetime": "2025-01-20T18:10:00Z",
                    "price": 520,
                    "format_id": 1,
                    "external_link": "https:\/\/karofilm.ru\/order\/session\/376048511"
                },
                {
                    "kinoplan_release_id": 22371,
                    "pushkin_card": false,
                    "datetime": "2025-01-21T10:40:00Z",
                    "price": 420,
                    "format_id": 1,
                    "external_link": "https:\/\/karofilm.ru\/order\/session\/376048522"
                },
                {
                    "kinoplan_release_id": 22371,
                    "pushkin_card": false,
                    "datetime": "2025-01-21T18:10:00Z",
                    "price": 520,
                    "format_id": 1,
                    "external_link": "https:\/\/karofilm.ru\/order\/session\/376048540"
                },
                {
                    "kinoplan_release_id": 22371,
                    "pushkin_card": false,
                    "datetime": "2025-01-22T10:40:00Z",
                    "price": 420,
                    "format_id": 1,
                    "external_link": "https:\/\/karofilm.ru\/order\/session\/376048552"
                },
                {
                    "kinoplan_release_id": 22371,
                    "pushkin_card": false,
                    "datetime": "2025-01-22T17:30:00Z",
                    "price": 520,
                    "format_id": 1,
                    "external_link": "https:\/\/karofilm.ru\/order\/session\/376050207"
                },
                {
                    "kinoplan_release_id": 22096,
                    "pushkin_card": false,
                    "datetime": "2025-01-16T11:00:00Z",
                    "price": 470,
                    "format_id": 1,
                    "external_link": "https:\/\/karofilm.ru\/order\/session\/376048372"
                },
                {
                    "kinoplan_release_id": 22096,
                    "pushkin_card": false,
                    "datetime": "2025-01-17T11:00:00Z",
                    "price": 470,
                    "format_id": 1,
                    "external_link": "https:\/\/karofilm.ru\/order\/session\/376048402"
                },
                {
                    "kinoplan_release_id": 22096,
                    "pushkin_card": false,
                    "datetime": "2025-01-18T11:00:00Z",
                    "price": 600,
                    "format_id": 1,
                    "external_link": "https:\/\/karofilm.ru\/order\/session\/376048432"
                },
                {
                    "kinoplan_release_id": 22096,
                    "pushkin_card": false,
                    "datetime": "2025-01-19T11:00:00Z",
                    "price": 600,
                    "format_id": 1,
                    "external_link": "https:\/\/karofilm.ru\/order\/session\/376048463"
                },
                {
                    "kinoplan_release_id": 22096,
                    "pushkin_card": false,
                    "datetime": "2025-01-20T11:00:00Z",
                    "price": 420,
                    "format_id": 1,
                    "external_link": "https:\/\/karofilm.ru\/order\/session\/376048494"
                },
                {
                    "kinoplan_release_id": 22096,
                    "pushkin_card": false,
                    "datetime": "2025-01-21T11:00:00Z",
                    "price": 420,
                    "format_id": 1,
                    "external_link": "https:\/\/karofilm.ru\/order\/session\/376048523"
                },
                {
                    "kinoplan_release_id": 22096,
                    "pushkin_card": false,
                    "datetime": "2025-01-22T11:00:00Z",
                    "price": 420,
                    "format_id": 1,
                    "external_link": "https:\/\/karofilm.ru\/order\/session\/376048553"
                },
                {
                    "kinoplan_release_id": 22193,
                    "pushkin_card": false,
                    "datetime": "2025-01-16T11:25:00Z",
                    "price": 470,
                    "format_id": 1,
                    "external_link": "https:\/\/karofilm.ru\/order\/session\/376048374"
                },
                {
                    "kinoplan_release_id": 22193,
                    "pushkin_card": false,
                    "datetime": "2025-01-16T17:15:00Z",
                    "price": 570,
                    "format_id": 1,
                    "external_link": "https:\/\/karofilm.ru\/order\/session\/376048386"
                },
                {
                    "kinoplan_release_id": 22193,
                    "pushkin_card": false,
                    "datetime": "2025-01-17T11:25:00Z",
                    "price": 470,
                    "format_id": 1,
                    "external_link": "https:\/\/karofilm.ru\/order\/session\/376048404"
                },
                {
                    "kinoplan_release_id": 22193,
                    "pushkin_card": false,
                    "datetime": "2025-01-17T17:15:00Z",
                    "price": 570,
                    "format_id": 1,
                    "external_link": "https:\/\/karofilm.ru\/order\/session\/376048416"
                },
                {
                    "kinoplan_release_id": 22193,
                    "pushkin_card": false,
                    "datetime": "2025-01-18T11:25:00Z",
                    "price": 600,
                    "format_id": 1,
                    "external_link": "https:\/\/karofilm.ru\/order\/session\/376048433"
                },
                {
                    "kinoplan_release_id": 22193,
                    "pushkin_card": false,
                    "datetime": "2025-01-18T17:15:00Z",
                    "price": 700,
                    "format_id": 1,
                    "external_link": "https:\/\/karofilm.ru\/order\/session\/376048447"
                },
                {
                    "kinoplan_release_id": 22193,
                    "pushkin_card": false,
                    "datetime": "2025-01-19T11:25:00Z",
                    "price": 600,
                    "format_id": 1,
                    "external_link": "https:\/\/karofilm.ru\/order\/session\/376048464"
                },
                {
                    "kinoplan_release_id": 22193,
                    "pushkin_card": false,
                    "datetime": "2025-01-19T17:15:00Z",
                    "price": 700,
                    "format_id": 1,
                    "external_link": "https:\/\/karofilm.ru\/order\/session\/376048478"
                },
                {
                    "kinoplan_release_id": 22193,
                    "pushkin_card": false,
                    "datetime": "2025-01-20T11:25:00Z",
                    "price": 420,
                    "format_id": 1,
                    "external_link": "https:\/\/karofilm.ru\/order\/session\/376048496"
                },
                {
                    "kinoplan_release_id": 22193,
                    "pushkin_card": false,
                    "datetime": "2025-01-20T17:15:00Z",
                    "price": 520,
                    "format_id": 1,
                    "external_link": "https:\/\/karofilm.ru\/order\/session\/376048508"
                },
                {
                    "kinoplan_release_id": 22193,
                    "pushkin_card": false,
                    "datetime": "2025-01-21T11:25:00Z",
                    "price": 420,
                    "format_id": 1,
                    "external_link": "https:\/\/karofilm.ru\/order\/session\/376048525"
                },
                {
                    "kinoplan_release_id": 22193,
                    "pushkin_card": false,
                    "datetime": "2025-01-21T17:15:00Z",
                    "price": 520,
                    "format_id": 1,
                    "external_link": "https:\/\/karofilm.ru\/order\/session\/376048537"
                },
                {
                    "kinoplan_release_id": 22193,
                    "pushkin_card": false,
                    "datetime": "2025-01-22T11:25:00Z",
                    "price": 420,
                    "format_id": 1,
                    "external_link": "https:\/\/karofilm.ru\/order\/session\/376048555"
                },
                {
                    "kinoplan_release_id": 22193,
                    "pushkin_card": false,
                    "datetime": "2025-01-22T17:15:00Z",
                    "price": 520,
                    "format_id": 1,
                    "external_link": "https:\/\/karofilm.ru\/order\/session\/376048567"
                },
                {
                    "kinoplan_release_id": 22672,
                    "pushkin_card": false,
                    "datetime": "2025-01-16T13:15:00Z",
                    "price": 470,
                    "format_id": 1,
                    "external_link": "https:\/\/karofilm.ru\/order\/session\/376048378"
                },
                {
                    "kinoplan_release_id": 22672,
                    "pushkin_card": false,
                    "datetime": "2025-01-17T13:15:00Z",
                    "price": 470,
                    "format_id": 1,
                    "external_link": "https:\/\/karofilm.ru\/order\/session\/376048408"
                },
                {
                    "kinoplan_release_id": 22672,
                    "pushkin_card": false,
                    "datetime": "2025-01-18T14:30:00Z",
                    "price": 700,
                    "format_id": 1,
                    "external_link": "https:\/\/karofilm.ru\/order\/session\/376048441"
                },
                {
                    "kinoplan_release_id": 22672,
                    "pushkin_card": false,
                    "datetime": "2025-01-19T14:30:00Z",
                    "price": 700,
                    "format_id": 1,
                    "external_link": "https:\/\/karofilm.ru\/order\/session\/376048472"
                },
                {
                    "kinoplan_release_id": 22672,
                    "pushkin_card": false,
                    "datetime": "2025-01-20T13:15:00Z",
                    "price": 420,
                    "format_id": 1,
                    "external_link": "https:\/\/karofilm.ru\/order\/session\/376048500"
                },
                {
                    "kinoplan_release_id": 22672,
                    "pushkin_card": false,
                    "datetime": "2025-01-21T13:15:00Z",
                    "price": 420,
                    "format_id": 1,
                    "external_link": "https:\/\/karofilm.ru\/order\/session\/376048529"
                },
                {
                    "kinoplan_release_id": 22672,
                    "pushkin_card": false,
                    "datetime": "2025-01-22T13:15:00Z",
                    "price": 420,
                    "format_id": 1,
                    "external_link": "https:\/\/karofilm.ru\/order\/session\/376048559"
                },
                {
                    "kinoplan_release_id": 20883,
                    "pushkin_card": true,
                    "datetime": "2025-01-19T12:30:00Z",
                    "price": 700,
                    "format_id": 1,
                    "external_link": "https:\/\/karofilm.ru\/order\/session\/376048467"
                },
                {
                    "kinoplan_release_id": 17789,
                    "pushkin_card": false,
                    "datetime": "2025-02-14T19:30:00Z",
                    "price": 570,
                    "format_id": 1,
                    "external_link": "https:\/\/karofilm.ru\/order\/session\/376030894"
                },
                {
                    "kinoplan_release_id": 17789,
                    "pushkin_card": false,
                    "datetime": "2025-02-15T19:30:00Z",
                    "price": 700,
                    "format_id": 1,
                    "external_link": "https:\/\/karofilm.ru\/order\/session\/376030895"
                },
                {
                    "kinoplan_release_id": 17789,
                    "pushkin_card": false,
                    "datetime": "2025-02-16T19:30:00Z",
                    "price": 700,
                    "format_id": 1,
                    "external_link": "https:\/\/karofilm.ru\/order\/session\/376030896"
                },
                {
                    "kinoplan_release_id": 17789,
                    "pushkin_card": false,
                    "datetime": "2025-02-17T19:30:00Z",
                    "price": 520,
                    "format_id": 1,
                    "external_link": "https:\/\/karofilm.ru\/order\/session\/376030897"
                },
                {
                    "kinoplan_release_id": 17789,
                    "pushkin_card": false,
                    "datetime": "2025-02-18T19:30:00Z",
                    "price": 520,
                    "format_id": 1,
                    "external_link": "https:\/\/karofilm.ru\/order\/session\/376030898"
                },
                {
                    "kinoplan_release_id": 17789,
                    "pushkin_card": false,
                    "datetime": "2025-02-19T19:30:00Z",
                    "price": 520,
                    "format_id": 1,
                    "external_link": "https:\/\/karofilm.ru\/order\/session\/376030899"
                }
            ]
        }
    ]
}